myconso/__init__.py
myconso/api.py
myconso/cli.py
myconso/middlewares.py
myconso/utils.py
myconso-0.0.2.dist-info/METADATA
myconso-0.0.2.dist-info/WHEEL
myconso-0.0.2.dist-info/entry_points.txt
myconso-0.0.2.dist-info/RECORD
