Metadata-Version: 2.4
Name: myconso
Version: 0.0.2
Summary: Async Python client to interact with myconso.net API
Project-URL: homepage, https://github.com/remijouannet/myconso.py
Project-URL: repository, https://github.com/remijouannet/myconso.py
Author-email: Rémi Jouannet <remijouannet@gmail.com>
Requires-Python: >=3.10
Requires-Dist: aiohttp
Requires-Dist: aiohttp-retry>=2.9.1
Requires-Dist: pyjwt[crypto]
